p5p5/CONTRIBUTING.md
p5p5/LICENSE.txt
p5p5/__init__.py
p5p5/__main__.py
p5p5/p5p5.py
p5p5-5.0.1.dist-info/LICENSE.txt
p5p5-5.0.1.dist-info/METADATA
p5p5-5.0.1.dist-info/WHEEL
p5p5-5.0.1.dist-info/entry_points.txt
p5p5-5.0.1.dist-info/top_level.txt
p5p5-5.0.1.dist-info/RECORD
